dutchtext2num_py-0.1.0.dist-info/METADATA
dutchtext2num_py-0.1.0.dist-info/WHEEL
text2num_py/__init__.py
text2num_py/text2num_py.cpython-311-darwin.so
dutchtext2num_py-0.1.0.dist-info/RECORD
