Metadata-Version: 2.4
Name: dutchtext2num-py
Version: 0.1.0
Summary: Convert Dutch written numbers to digits using Rust + Python
Author-email: Your Name <iskajjanssen1@hotmail.com>
License: MIT
Requires-Python: >=3.7
